alt_lk/__init__.py
alt_lk/alt/Alt.py
alt_lk/alt/__init__.py
alt_lk/core/BBox.py
alt_lk/core/LatLng.py
alt_lk/core/Resolution.py
alt_lk/core/__init__.py
alt_lk/data/AltFile.py
alt_lk/data/GeoTIFFFile.py
alt_lk/data/__init__.py
utils_future/Example.py
utils_future/File.py
utils_future/SparseArrayFile.py
utils_future/__init__.py
alt_lk_nuuuwan-1.1.0.dist-info/METADATA
alt_lk_nuuuwan-1.1.0.dist-info/WHEEL
alt_lk_nuuuwan-1.1.0.dist-info/top_level.txt
alt_lk_nuuuwan-1.1.0.dist-info/RECORD
